comprehemd/VERSION
comprehemd/__init__.py
comprehemd/fence.py
comprehemd/parser.py
comprehemd/py.typed
comprehemd/blocks/__init__.py
comprehemd/blocks/block.py
comprehemd/blocks/code.py
comprehemd/blocks/empty.py
comprehemd/blocks/heading.py
comprehemd/blocks/py.typed
comprehemd/code_patterns/__init__.py
comprehemd/code_patterns/backticks.py
comprehemd/code_patterns/base.py
comprehemd/code_patterns/indent.py
comprehemd/code_patterns/py.typed
comprehemd/code_patterns/tildes.py
comprehemd-1.0.0.dist-info/LICENSE
comprehemd-1.0.0.dist-info/METADATA
comprehemd-1.0.0.dist-info/WHEEL
comprehemd-1.0.0.dist-info/top_level.txt
comprehemd-1.0.0.dist-info/RECORD
