Metadata-Version: 2.1
Name: comprehemd
Version: 1.0.0
Summary: Markdown parser
Home-page: https://github.com/cariad/comprehemd
Author: Cariad Eccleston
Author-email: cariad@cariad.earth
License: MIT
Platform: UNKNOWN
Classifier: Development Status :: 5 - Production/Stable
Classifier: License :: OSI Approved :: MIT License
Classifier: Natural Language :: English
Classifier: Programming Language :: Python :: 3 :: Only
Classifier: Programming Language :: Python :: 3.10
Classifier: Programming Language :: Python :: 3.8
Classifier: Programming Language :: Python :: 3.9
Classifier: Typing :: Typed
Requires-Python: >=3.8
License-File: LICENSE
